LICENSE.txt
MANIFEST.in
README.md
description.txt
setup.cfg
setup.py
versioneer.py
PyDSD.egg-info/PKG-INFO
PyDSD.egg-info/SOURCES.txt
PyDSD.egg-info/dependency_links.txt
PyDSD.egg-info/requires.txt
PyDSD.egg-info/top_level.txt
pydsd/DSDProcessor.py
pydsd/DSR.py
pydsd/DropSizeDistribution.py
pydsd/__init__.py
pydsd/_version.py
pydsd/aux_readers/ARM_APU_reader.py
pydsd/aux_readers/ARM_JWD_Reader.py
pydsd/aux_readers/ARM_Vdis_Reader.py
pydsd/aux_readers/GPMApuWallopsRawReader.py
pydsd/aux_readers/NASA_2DVD_reader.py
pydsd/aux_readers/__init__.py
pydsd/aux_readers/read_2ds.py
pydsd/aux_readers/read_hvps.py
pydsd/fit/__init__.py
pydsd/fit/ua98.py
pydsd/io/ARM_vdisdrops_reader.py
pydsd/io/Image2DReader.py
pydsd/io/JWDReader.py
pydsd/io/NetCDFWriter.py
pydsd/io/ParsivelNasaGVReader.py
pydsd/io/ParsivelReader.py
pydsd/io/__init__.py
pydsd/io/common.py
pydsd/partition/__init__.py
pydsd/partition/cs_partition.py
pydsd/plot/__init__.py
pydsd/plot/plot.py
pydsd/utility/__init__.py
pydsd/utility/configuration.py
pydsd/utility/dielectric.py
pydsd/utility/expfit.py
pydsd/utility/filter.py
pydsd/utility/metadata.json
pydsd/utility/ts_utility.py