Metadata-Version: 1.1
Name: PyDSD
Version: 1.0.6.2
Summary: Python Disdrometer Processing
Home-page: http://pypi.python.org/pypi/PyDSD/
Author: Joseph C. Hardin, Nick Guy
Author-email: josephhardinee@gmail.com
License: LICENSE.txt
Platform: UNKNOWN
Classifier: Development Status :: 3 - Alpha
Classifier: Environment :: Console
